LICENSE.txt
MANIFEST.in
README.rst
requirements.txt
setup.cfg
setup.py
versioneer.py
docs/source/api.rst
docs/source/changelog.rst
docs/source/developer.rst
docs/source/fuse.rst
docs/source/index.rst
elements_custom_gcsfs.egg-info/PKG-INFO
elements_custom_gcsfs.egg-info/SOURCES.txt
elements_custom_gcsfs.egg-info/dependency_links.txt
elements_custom_gcsfs.egg-info/not-zip-safe
elements_custom_gcsfs.egg-info/requires.txt
elements_custom_gcsfs.egg-info/top_level.txt
gcsfs/__init__.py
gcsfs/_version.py
gcsfs/checkers.py
gcsfs/core.py
gcsfs/credentials.py
gcsfs/dask_link.py
gcsfs/mapping.py
gcsfs/retry.py
gcsfs/cli/__init__.py
gcsfs/cli/gcsfuse.py
gcsfs/tests/__init__.py
gcsfs/tests/conftest.py
gcsfs/tests/settings.py
gcsfs/tests/test_checkers.py
gcsfs/tests/test_core.py
gcsfs/tests/test_credentials.py
gcsfs/tests/test_fuse.py
gcsfs/tests/test_manyopens.py
gcsfs/tests/test_mapping.py
gcsfs/tests/test_retry.py
gcsfs/tests/utils.py