Metadata-Version: 2.1
Name: elements-custom-gcsfs
Version: 2021.11.0.1
Summary: Convenient Filesystem interface over GCS
Home-page: https://github.com/fsspec/gcsfs
Maintainer: Martin Durant
Maintainer-email: mdurant@anaconda.com
License: BSD
Keywords: google-cloud-storage,gcloud,file-system
Classifier: Development Status :: 4 - Beta
Classifier: Intended Audience :: Developers
Classifier: License :: OSI Approved :: BSD License
Classifier: Operating System :: OS Independent
Classifier: Programming Language :: Python :: 3.6
Classifier: Programming Language :: Python :: 3.7
Classifier: Programming Language :: Python :: 3.8
Classifier: Programming Language :: Python :: 3.9
Requires-Python: >=3.6
Provides-Extra: gcsfuse
Provides-Extra: crc
License-File: LICENSE.txt
